{
  "updated": "2026-04-11 12:39:52",
  "updated_date": "2026-04-11",
  "funds": {
    "159222": {
      "code": "159222",
      "name": "自由现金流ETF易方达",
      "price": 1.4106,
      "change_pct": 0.5,
      "date": "2026-04-10"
    },
    "563020": {
      "code": "563020",
      "name": "红利低波ETF易方达",
      "price": 1.191,
      "change_pct": -0.08,
      "date": "2026-04-10"
    },
    "513650": {
      "code": "513650",
      "name": "标普500ETF南方",
      "price": 1.6786,
      "change_pct": -0.56,
      "date": "2026-04-11"
    },
    "518680": {
      "code": "518680",
      "name": "金ETF富国",
      "price": 10.3603,
      "change_pct": 0.0,
      "date": "2026-04-10"
    }
  },
  "index": {
    "sh000001": {
      "code": "000001",
      "name": "上证指数",
      "price": 3986.22,
      "change_pct": 0.51
    },
    "spx": {
      "code": "100.SPX",
      "name": "S&P 500",
      "price": 6816.89,
      "change_pct": -0.11
    }
  }
}